setup.py
dthreads/__init__.py
dthreads/version.py
dthreads.egg-info/PKG-INFO
dthreads.egg-info/SOURCES.txt
dthreads.egg-info/dependency_links.txt
dthreads.egg-info/not-zip-safe
dthreads.egg-info/pbr.json
dthreads.egg-info/requires.txt
dthreads.egg-info/top_level.txt