Metadata-Version: 1.1
Name: dthreads
Version: 0.0.1
Summary: Object-like dictionaries.
Home-page: http://bnlucas.github.io/python-dthreads
Author: Nathan Lucas
Author-email: bnlucas@outlook.com
License: 
Download-URL: https://github.com/bnlucas/python-dthreads/archive/master.zip
Keywords: dict,object,mapping,collection
Platform: UNKNOWN
Classifier: Development Status :: 5 - Production/Stable
Classifier: Programming Language :: Python
Classifier: License :: OSI Approved :: Apache Software License
Classifier: Intended Audience :: Developers
Classifier: Operating System :: OS Independent
Classifier: Topic :: Utilities
